README.md
setup.py
frontdoor/__init__.py
frontdoor/__init__.pyi
frontdoor/py.typed
frontdoor.egg-info/PKG-INFO
frontdoor.egg-info/SOURCES.txt
frontdoor.egg-info/dependency_links.txt
frontdoor.egg-info/top_level.txt