Metadata-Version: 1.0
Name: frontdoor
Version: 0.1.5
Summary: Aids the creation of "front door" scripts.
Home-page: UNKNOWN
Author: Tim Simpson
Author-email: UNKNOWN
License: MIT
Platform: UNKNOWN
